slist/__init__.py
slist/py.typed
slist/pydantic_compat.py
slist-0.3.15.dist-info/LICENSE
slist-0.3.15.dist-info/METADATA
slist-0.3.15.dist-info/WHEEL
slist-0.3.15.dist-info/RECORD
