Metadata-Version: 2.3
Name: slist
Version: 0.3.15
Summary: A typesafe list with more method chaining!
License: MIT
Author: James Chua
Author-email: chuajamessh@gmail.com
Requires-Python: >=3.8,<4.0
Classifier: Development Status :: 2 - Pre-Alpha
Classifier: Intended Audience :: Developers
Classifier: License :: OSI Approved :: MIT License
Classifier: Natural Language :: English
Classifier: Programming Language :: Python :: 3
Classifier: Programming Language :: Python :: 3.8
Classifier: Programming Language :: Python :: 3.9
Classifier: Programming Language :: Python :: 3.10
Classifier: Programming Language :: Python :: 3.11
Classifier: Programming Language :: Python :: 3.12
Classifier: Programming Language :: Python :: 3.13
Classifier: Programming Language :: Python :: 3.7
Provides-Extra: dev
Provides-Extra: doc
Provides-Extra: test
Requires-Dist: typing-extensions (>=4.0.0,<5.0.0)
Project-URL: Homepage, https://github.com/thejaminator/slist
